bitcoinx/__init__.py
bitcoinx/address.py
bitcoinx/aes.py
bitcoinx/base58.py
bitcoinx/bip32.py
bitcoinx/cashaddr.py
bitcoinx/consts.py
bitcoinx/errors.py
bitcoinx/hashes.py
bitcoinx/headers.py
bitcoinx/interpreter.py
bitcoinx/keys.py
bitcoinx/limited_stack.py
bitcoinx/merkle.py
bitcoinx/misc.py
bitcoinx/mnemonic.py
bitcoinx/packing.py
bitcoinx/script.py
bitcoinx/signature.py
bitcoinx/tx.py
bitcoinx/work.py
bitcoinx/data/chinese_simplified.txt
bitcoinx/data/electrum_old.txt
bitcoinx/data/english.txt
bitcoinx/data/japanese.txt
bitcoinx/data/spanish.txt
bitcoinX-0.9.dist-info/LICENCE
bitcoinX-0.9.dist-info/METADATA
bitcoinX-0.9.dist-info/WHEEL
bitcoinX-0.9.dist-info/top_level.txt
bitcoinX-0.9.dist-info/RECORD
